kythera_kdx/__init__.py
kythera_kdx/addin.py
kythera_kdx/authenticated_client.py
kythera_kdx/exceptions.py
kythera_kdx/funds.py
kythera_kdx/globals.py
kythera_kdx/instrument_groups.py
kythera_kdx/instrument_parameters.py
kythera_kdx/instruments.py
kythera_kdx/intraday.py
kythera_kdx/kythera_kdx.py
kythera_kdx/models.py
kythera_kdx/models_v1.py
kythera_kdx/pnl.py
kythera_kdx/positions.py
kythera_kdx/prices.py
kythera_kdx/risk_factors.py
kythera_kdx/trades.py
kythera_kdx-0.1.0.dist-info/licenses/LICENSE
kythera_kdx-0.1.0.dist-info/METADATA
kythera_kdx-0.1.0.dist-info/WHEEL
kythera_kdx-0.1.0.dist-info/top_level.txt
kythera_kdx-0.1.0.dist-info/RECORD
