Metadata-Version: 2.4
Name: kythera-kdx
Version: 0.1.0
Summary: A Python wrapper for the Kythera API
Home-page: https://github.com/rportela/kythera-api-wrapper
Author: Your Name
Author-email: Rodrigo Portela <rodrigo.portela@gmail.com>
License-Expression: MIT
Project-URL: Homepage, https://github.com/rportela/kythera-api-wrapper
Project-URL: Repository, https://github.com/rportela/kythera-api-wrapper
Project-URL: Issues, https://github.com/rportela/kythera-api-wrapper/issues
Keywords: kythera,api,wrapper,kdx
Classifier: Development Status :: 3 - Alpha
Classifier: Intended Audience :: Developers
Classifier: Programming Language :: Python :: 3
Classifier: Programming Language :: Python :: 3.8
Classifier: Programming Language :: Python :: 3.9
Classifier: Programming Language :: Python :: 3.10
Classifier: Programming Language :: Python :: 3.11
Classifier: Programming Language :: Python :: 3.12
Requires-Python: >=3.8
License-File: LICENSE
Requires-Dist: httpx>=0.25.0
Requires-Dist: pydantic>=2.0.0
Requires-Dist: msal>=1.24.0
Requires-Dist: msal-extensions>=1.0.0
Requires-Dist: pandas
Provides-Extra: dev
Requires-Dist: pytest>=7.0.0; extra == "dev"
Requires-Dist: pytest-cov>=4.0.0; extra == "dev"
Requires-Dist: black>=23.0.0; extra == "dev"
Requires-Dist: isort>=5.0.0; extra == "dev"
Requires-Dist: flake8>=6.0.0; extra == "dev"
Requires-Dist: mypy>=1.0.0; extra == "dev"
Requires-Dist: pre-commit>=3.0.0; extra == "dev"
Dynamic: license-file
